<?xml version="1.0" encoding="UTF-8"?>
<!DOCTYPE hibernate-reverse-engineering PUBLIC "-//Hibernate/Hibernate Reverse Engineering DTD 3.0//EN" "http://hibernate.sourceforge.net/hibernate-reverse-engineering-3.0.dtd">
<hibernate-reverse-engineering>
  <schema-selection match-catalog="pdconstructor" match-schema="public"/>
  <table-filter match-name="ESCOLHA_CLASSE_TEXTO"/>
  <table-filter match-name="ALOCACAO_TEXTO"/>
  <table-filter match-name="LIBARACAO_BASE_TEXTO"/>
  <table-filter match-name="USUARIO"/>
  <table-filter match-name="PERFIL"/>
  <table-filter match-name="CLASSIFICACAO_TEXTO"/>
  <table-filter match-name="BASE_TEXTO"/>
</hibernate-reverse-engineering>
